{
  "project_info": {
    "project_number": "323388033463",
    "project_id": "chatappflutter-5b0a8",
    "storage_bucket": "chatappflutter-5b0a8.appspot.com"
  },
  "client": [
    {
      "client_info": {
        "mobilesdk_app_id": "1:323388033463:android:8a6b8041d8959f9e920032",
        "android_client_info": {
          "package_name": "com.example.my_project"
        }
      },
      "oauth_client": [],
      "api_key": [
        {
          "current_key": "AIzaSyCt8HKa4-1IXcmaNW8KAhD8dZZeS3veVEw"
        }
      ],
      "services": {
        "appinvite_service": {
          "other_platform_oauth_client": []
        }
      }
    }
  ],
  "configuration_version": "1"
}